cencori/__init__.py
cencori/ai.py
cencori/client.py
cencori/errors.py
cencori/types.py
cencori-0.1.0.dist-info/METADATA
cencori-0.1.0.dist-info/WHEEL
cencori-0.1.0.dist-info/RECORD
