Metadata-Version: 2.4
Name: cencori
Version: 0.1.0
Summary: Official Python SDK for Cencori - AI Infrastructure for Production
Project-URL: Homepage, https://cencori.com
Project-URL: Documentation, https://cencori.com/docs
Project-URL: Repository, https://github.com/cencori/cencori-python
Author-email: FohnAI <support@cencori.com>
License-Expression: MIT
Keywords: ai,anthropic,api,gateway,gemini,infrastructure,llm,openai
Classifier: Development Status :: 4 - Beta
Classifier: Intended Audience :: Developers
Classifier: License :: OSI Approved :: MIT License
Classifier: Programming Language :: Python :: 3
Classifier: Programming Language :: Python :: 3.8
Classifier: Programming Language :: Python :: 3.9
Classifier: Programming Language :: Python :: 3.10
Classifier: Programming Language :: Python :: 3.11
Classifier: Programming Language :: Python :: 3.12
Classifier: Topic :: Scientific/Engineering :: Artificial Intelligence
Classifier: Topic :: Software Development :: Libraries :: Python Modules
Requires-Python: >=3.8
Requires-Dist: httpx>=0.24.0
Provides-Extra: dev
Requires-Dist: mypy>=1.0; extra == 'dev'
Requires-Dist: pytest-asyncio>=0.21; extra == 'dev'
Requires-Dist: pytest>=7.0; extra == 'dev'
Requires-Dist: ruff>=0.1; extra == 'dev'
